{
  "kind": "youtube#searchListResponse",
  "etag": "xsVoiXQ6sfGxR2Z5MeVWHVAZB10",
  "nextPageToken": "CAoQAA",
  "regionCode": "US",
  "pageInfo": {
    "totalResults": 273,
    "resultsPerPage": 10
  },
  "items": [
    {
      "kind": "youtube#searchResult",
      "etag": "JBPWtiqTmXidRefAIM5GYdVE-sg",
      "id": {
        "kind": "youtube#video",
        "videoId": "wE4iaGEV-Y4"
      },
      "snippet": {
        "publishedAt": "2026-02-24T02:30:44Z",
        "channelId": "UCLuWhw8fYakYDzM9SlNXVKg",
        "title": "A sa\u00edda que vem de Deus - Pr. Luiz Carlos",
        "description": "Culto de Domingo (Noite) 22 de fevereiro Pr. Luiz Carlos.",
        "thumbnails": {
          "default": {
            "url": "https://i.ytimg.com/vi/wE4iaGEV-Y4/default.jpg",
            "width": 120,
            "height": 90
          },
          "medium": {
            "url": "https://i.ytimg.com/vi/wE4iaGEV-Y4/mqdefault.jpg",
            "width": 320,
            "height": 180
          },
          "high": {
            "url": "https://i.ytimg.com/vi/wE4iaGEV-Y4/hqdefault.jpg",
            "width": 480,
            "height": 360
          }
        },
        "channelTitle": "IGREJA NOVA VIDA DE BOTAFOGO",
        "liveBroadcastContent": "none",
        "publishTime": "2026-02-24T02:30:44Z"
      }
    },
    {
      "kind": "youtube#searchResult",
      "etag": "GK72YIO7RUFwjyDPzjylyxpX2nk",
      "id": {
        "kind": "youtube#video",
        "videoId": "UMQZPT4MKgw"
      },
      "snippet": {
        "publishedAt": "2026-02-24T01:51:29Z",
        "channelId": "UCLuWhw8fYakYDzM9SlNXVKg",
        "title": "Chega de Apar\u00eancia Espiritual - Pra. Daniela Neves",
        "description": "Culto de Domingo (Manh\u00e3) 22 de fevereiro Pr. Daniela Neves.",
        "thumbnails": {
          "default": {
            "url": "https://i.ytimg.com/vi/UMQZPT4MKgw/default.jpg",
            "width": 120,
            "height": 90
          },
          "medium": {
            "url": "https://i.ytimg.com/vi/UMQZPT4MKgw/mqdefault.jpg",
            "width": 320,
            "height": 180
          },
          "high": {
            "url": "https://i.ytimg.com/vi/UMQZPT4MKgw/hqdefault.jpg",
            "width": 480,
            "height": 360
          }
        },
        "channelTitle": "IGREJA NOVA VIDA DE BOTAFOGO",
        "liveBroadcastContent": "none",
        "publishTime": "2026-02-24T01:51:29Z"
      }
    },
    {
      "kind": "youtube#searchResult",
      "etag": "mHnwmSnIE2s6RymRFOA0XORamjQ",
      "id": {
        "kind": "youtube#video",
        "videoId": "A_TnWCJ5_6A"
      },
      "snippet": {
        "publishedAt": "2026-02-15T17:30:34Z",
        "channelId": "UCLuWhw8fYakYDzM9SlNXVKg",
        "title": "A ORDEM \u00c9 AVAN\u00c7AR! - Pr. Marcio Soares",
        "description": "Culto de Domingo (Manh\u00e3) 15 de fevereiro Pr. Marcio Soares.",
        "thumbnails": {
          "default": {
            "url": "https://i.ytimg.com/vi/A_TnWCJ5_6A/default.jpg",
            "width": 120,
            "height": 90
          },
          "medium": {
            "url": "https://i.ytimg.com/vi/A_TnWCJ5_6A/mqdefault.jpg",
            "width": 320,
            "height": 180
          },
          "high": {
            "url": "https://i.ytimg.com/vi/A_TnWCJ5_6A/hqdefault.jpg",
            "width": 480,
            "height": 360
          }
        },
        "channelTitle": "IGREJA NOVA VIDA DE BOTAFOGO",
        "liveBroadcastContent": "none",
        "publishTime": "2026-02-15T17:30:34Z"
      }
    }
  ]
}